grey_verifier/__init__.py
grey_verifier-0.1.7.dist-info/METADATA
grey_verifier-0.1.7.dist-info/WHEEL
grey_verifier-0.1.7.dist-info/entry_points.txt
grey_verifier-0.1.7.dist-info/licenses/LICENSE
grey_verifier-0.1.7.dist-info/RECORD
