Metadata-Version: 2.3
Name: grey_verifier
Version: 0.1.7
Summary: Smart SMTP email verifier which can even bypass greylisting!
Project-URL: Homepage, https://github.com/yaroslaff/grey-verifier
Project-URL: Issues, https://github.com/yaroslaff/grey-verifier/issues
Author-email: Yaroslav Polyakov <yaroslaff@gmail.com>
License-File: LICENSE
Keywords: MAIL FROM,RCPT TO,SMTP,bulk,e-mail,email,grey,greylist,greylisting,mail,mailfrom,validate,verifier
Classifier: License :: OSI Approved :: MIT License
Classifier: Operating System :: OS Independent
Classifier: Programming Language :: Python :: 3
Classifier: Topic :: Communications :: Email
Classifier: Topic :: Communications :: Email :: Address Book
Classifier: Topic :: Communications :: Email :: Filters
Requires-Python: >=3.8
Requires-Dist: dnspython
